README.rst
luhn.py
setup.py
luhn.egg-info/PKG-INFO
luhn.egg-info/SOURCES.txt
luhn.egg-info/dependency_links.txt
luhn.egg-info/top_level.txt