Metadata-Version: 1.0
Name: luhn
Version: 0.1.1
Summary: Generate and verify Luhn check digits
Home-page: https://github.com/mmcloughlin/luhn
Author: Michael McLoughlin
Author-email: mmcloughlin@gmail.com
License: MIT
Platform: UNKNOWN
